{
  "id": "0927fa2aed36",
  "title": "Bihar May Get A BJP Chief Minister, 1 Deputy, 15 Ministers From JDU: Sources",
  "description": "Nitish Kumar, who served as Bihar's longest-tenured Chief Minister for over two decades, filed his nomination for the Rajya Sabha elections on Thursday.",
  "link": "https://www.ndtv.com/india-news/bihar-may-get-a-bjp-chief-minister-1-deputy-15-ministers-from-jdu-sources-nitish-kumar-resigns-rajya-sabha-bihar-politics-11176859#publisher=newsstand",
  "date": "2026-03-06",
  "source_id": "ndtv_india",
  "source_name": "NDTV - India",
  "source_short": "NDTV",
  "sectors": [
    "Health",
    "Digital & Technology",
    "Social Protection"
  ],
  "sector_slugs": [
    "health",
    "digital-technology",
    "social-protection"
  ],
  "type": "policy",
  "level": "central",
  "state": ""
}