{
  "id": "1725001faa37",
  "title": "Heat, rainfall deficit hit Kashmir’s ₹100-crore nursery industry",
  "description": "The unusual weather has disrupted the planting season, particularly for apple orchards, a key part of the region’s horticulture economy.",
  "link": "https://www.thehindubusinessline.com/news/heat-rainfall-deficit-hit-kashmirs-100-crore-nursery-industry/article70707451.ece",
  "date": "2026-03-05",
  "source_id": "business_line",
  "source_name": "BusinessLine - Economy",
  "source_short": "BL",
  "sectors": [
    "Digital & Technology",
    "Agriculture",
    "Finance & Economy"
  ],
  "sector_slugs": [
    "digital-technology",
    "agriculture",
    "finance-economy"
  ],
  "type": "policy",
  "level": "central",
  "state": ""
}