{
  "id": "33527833e0ed",
  "title": "Rajya Sabha elections: Congress renominates Chhattisgarh MP Phulo Devi Netam",
  "description": "Phulo Devi Netam hails from Kondagaon district in the tribal pocket of Bastar",
  "link": "https://www.thehindu.com/news/national/chhattisgarh/rajya-sabha-elections-congress-renominates-chhattisgarh-mp-phulo-devi-netam/article70706042.ece",
  "date": "2026-03-05",
  "source_id": "the_hindu_policy",
  "source_name": "The Hindu - National",
  "source_short": "The Hindu",
  "sectors": [
    "Digital & Technology",
    "Social Protection",
    "Energy"
  ],
  "sector_slugs": [
    "digital-technology",
    "social-protection",
    "energy"
  ],
  "type": "policy",
  "level": "central",
  "state": ""
}