{
  "id": "3a76df2ada32",
  "title": "Cochin International Airport to handle special cargo flight to Abu Dhabi",
  "description": "The shipment, organized by Fair Exports (India) Pvt. Ltd., Angamaly, includes around 12,000 packages of fresh fruits and vegetables with a total weight of approximately 80,000 kg",
  "link": "https://www.thehindubusinessline.com/economy/logistics/cochin-international-airport-to-handle-special-cargo-flight-to-abu-dhabi/article70707449.ece",
  "date": "2026-03-05",
  "source_id": "business_line",
  "source_name": "BusinessLine - Economy",
  "source_short": "BL",
  "sectors": [
    "Digital & Technology",
    "Transport & Infrastructure",
    "Trade & Commerce"
  ],
  "sector_slugs": [
    "digital-technology",
    "transport-infrastructure",
    "trade-commerce"
  ],
  "type": "policy",
  "level": "central",
  "state": ""
}