{
  "id": "3dd0a1d8928c",
  "title": "Prime Minister welcomes President of Finland Alexander Stubb to India",
  "description": "Government of India press release: Prime Minister welcomes President of Finland Alexander Stubb to India",
  "link": "https://pib.gov.in/PressReleseDetail.aspx?PRID=2235256",
  "date": "2026-03-04",
  "source_id": "state_pib_punjab",
  "source_name": "PIB Chandigarh (Punjab & Haryana)",
  "source_short": "PIB PB",
  "sectors": [
    "Social Protection",
    "Labour & Employment"
  ],
  "sector_slugs": [
    "social-protection",
    "labour-employment"
  ],
  "type": "announcement",
  "level": "state",
  "state": "Punjab"
}