{
  "id": "45c2686ca7eb",
  "title": "Amid spurt in small aircraft accidents, DGCA cracks whip with stricter oversight, penalties",
  "description": "",
  "link": "https://indianexpress.com/article/business/aviation/amid-spurt-in-small-aircraft-accidents-dgca-cracks-whip-with-stricter-oversight-penalties-10550452/",
  "date": "2026-02-24",
  "source_id": "indian_express_business",
  "source_name": "Indian Express - Business",
  "source_short": "IE Biz",
  "sectors": [
    "Digital & Technology",
    "Social Protection",
    "Trade & Commerce"
  ],
  "sector_slugs": [
    "digital-technology",
    "social-protection",
    "trade-commerce"
  ],
  "type": "policy",
  "level": "central",
  "state": ""
}