{
  "id": "6d1f5c0202d9",
  "title": "Ranveer Singh Promises Revenge in Dhurandhar 2 Trailer, RGV Says 'Stratospheric Level'",
  "description": "The 3-minute-25-second trailer starts with Singh returning with ferocious intensity in dual avatars, Jaskirat Singh Rangi and Hamza Ali Mazari.",
  "link": "https://www.deccanchronicle.com/entertainment/ranveer-singhs-dhurandhar-2-the-revenge-trailer-review-1942126",
  "date": "2026-03-07",
  "source_id": "dc_rss",
  "source_name": "Deccan Chronicle (RSS)",
  "source_short": "DC RSS",
  "sectors": [
    "Digital & Technology",
    "Social Protection",
    "Energy"
  ],
  "sector_slugs": [
    "digital-technology",
    "social-protection",
    "energy"
  ],
  "type": "policy",
  "level": "central",
  "state": ""
}