{
  "id": "8d6226b3ac86",
  "title": "Patience has Limits: Hezbollah Chief Warns Israel",
  "description": "During a televised address on Wednesday, Sheikh Qassem detailed the group’s commitment to the previous truce",
  "link": "https://www.deccanchronicle.com/world/patience-has-limits-hezbollah-chief-warns-israel-1941628",
  "date": "2026-03-05",
  "source_id": "dc_rss",
  "source_name": "Deccan Chronicle (RSS)",
  "source_short": "DC RSS",
  "sectors": [
    "Digital & Technology",
    "Energy"
  ],
  "sector_slugs": [
    "digital-technology",
    "energy"
  ],
  "type": "policy",
  "level": "central",
  "state": ""
}