{
  "id": "bddbd51ca681",
  "title": "'Full cooperation to new govt': Bihar CM Nitish Kumar's first remark on Rajya Sabha move",
  "description": "Nitish Kumar said he always wanted to become a member of both the Houses of the Bihar Legislature as well as both Houses of Parliament.",
  "link": "https://www.hindustantimes.com/india-news/full-cooperation-to-new-govt-bihar-cm-nitish-kumars-first-remark-on-rajya-sabha-move-101772689191007.html",
  "date": "2026-03-05",
  "source_id": "hindustan_times",
  "source_name": "Hindustan Times - India",
  "source_short": "HT",
  "sectors": [
    "Digital & Technology",
    "Social Protection"
  ],
  "sector_slugs": [
    "digital-technology",
    "social-protection"
  ],
  "type": "policy",
  "level": "central",
  "state": ""
}