{
  "id": "ce9a21bb77d5",
  "title": "West Asia conflict: Stranded Keralite students anxious about returning in time for semester exams",
  "description": "Parents back home, worried both about their children’s safety and academic future, scour portals for flight tickets, while making panic-stricken calls to colleges for reassurance",
  "link": "https://www.thehindu.com/news/national/kerala/west-asia-conflict-stranded-keralite-students-anxious-about-returning-in-time-for-semester-exams/article70715355.ece",
  "date": "2026-03-07",
  "source_id": "the_hindu_policy",
  "source_name": "The Hindu - National",
  "source_short": "The Hindu",
  "sectors": [
    "Child Rights & Youth",
    "Education",
    "Social Protection"
  ],
  "sector_slugs": [
    "child-rights-youth",
    "education",
    "social-protection"
  ],
  "type": "policy",
  "level": "central",
  "state": ""
}