{
  "id": "d2a86aa895a0",
  "title": "Reliance diverts diesel and jet fuel cargoes from Europe to Asia amid supply crunch",
  "description": "The tanker Advantage Life, carrying about 100,000 tonnes of diesel, and Navig8 Honor, loaded with roughly 75,000 tonnes of jet fuel, reversed course and are now heading to Southeast Asia, according to ship-tracking data",
  "link": "https://www.thehindubusinessline.com/markets/commodities/reliance-diverts-diesel-and-jet-fuel-cargoes-from-europe-to-asia-amid-supply-crunch/article70711557.ece",
  "date": "2026-03-06",
  "source_id": "business_line",
  "source_name": "BusinessLine - Economy",
  "source_short": "BL",
  "sectors": [
    "Digital & Technology",
    "Social Protection",
    "Energy"
  ],
  "sector_slugs": [
    "digital-technology",
    "social-protection",
    "energy"
  ],
  "type": "policy",
  "level": "central",
  "state": ""
}