{
  "id": "e4590d5a60b1",
  "title": "Tuhin Kanta Pandey: ‘We believe in optimal regulation, not too much, not too little’",
  "description": "",
  "link": "https://indianexpress.com/article/business/tuhin-kanta-pandey-we-believe-in-optimal-regulation-not-too-much-not-too-little-10560113/",
  "date": "2026-03-01",
  "source_id": "indian_express_business",
  "source_name": "Indian Express - Business",
  "source_short": "IE Biz",
  "sectors": [
    "Digital & Technology",
    "Energy"
  ],
  "sector_slugs": [
    "digital-technology",
    "energy"
  ],
  "type": "policy",
  "level": "central",
  "state": ""
}