{
  "id": "ecdd453d5b3e",
  "title": "Etihad resumes commercial flights as missile threat persists",
  "description": "Etihad says services remain subject to operational approvals and may be adjusted, depending on regional airspace conditions, and that not all destinations will operate daily",
  "link": "https://www.thehindubusinessline.com/economy/logistics/etihad-resumes-commercial-flights-as-missile-threat-persists/article70711729.ece",
  "date": "2026-03-06",
  "source_id": "business_line",
  "source_name": "BusinessLine - Economy",
  "source_short": "BL",
  "sectors": [
    "Digital & Technology",
    "Social Protection",
    "Defence & Security"
  ],
  "sector_slugs": [
    "digital-technology",
    "social-protection",
    "defence-security"
  ],
  "type": "policy",
  "level": "central",
  "state": ""
}