{
  "id": "f14e5998396c",
  "title": "Supreme Court annuls rape conviction of man citing marriage but with a condition",
  "description": "The criminal case arose out of what the SC described as an affair between the accused and the girl, who was a minor at the time of the sexual relationship.",
  "link": "https://www.hindustantimes.com/india-news/supreme-court-annuls-rape-conviction-of-man-citing-marriage-but-with-a-condition-101772864563328.html",
  "date": "2026-03-07",
  "source_id": "hindustan_times",
  "source_name": "Hindustan Times - India",
  "source_short": "HT",
  "sectors": [
    "Digital & Technology",
    "Health",
    "Social Protection"
  ],
  "sector_slugs": [
    "digital-technology",
    "health",
    "social-protection"
  ],
  "type": "policy",
  "level": "central",
  "state": ""
}